nereval.py
nereval-0.2.5.dist-info/METADATA
nereval-0.2.5.dist-info/RECORD
nereval-0.2.5.dist-info/WHEEL
nereval-0.2.5.dist-info/top_level.txt
