Metadata-Version: 2.1
Name: nereval
Version: 0.2.5
Summary: Evaluation script for named entity recognition systems based on F1 score.
Home-page: https://github.com/jantrienes/nereval
Author: Jan Trienes
Author-email: jan.trienes@googlemail.com
License: MIT
Keywords: ner,nlp,evaluation,f1_score,f1,linguistics,machine_learning
Platform: UNKNOWN
